semistaticsim/__init__.py
semistaticsim/spoof_hydra.py
semistaticsim/subproc.py
semistaticsim/datawrangling/__init__.py
semistaticsim/datawrangling/sssd.py
semistaticsim/groundtruth/__init__.py
semistaticsim/groundtruth/constants.py
semistaticsim/groundtruth/jax_polygon.py
semistaticsim/groundtruth/main.py
semistaticsim/groundtruth/objects.py
semistaticsim/groundtruth/procthor_object.py
semistaticsim/groundtruth/schedule.py
semistaticsim/groundtruth/schedule_generation.py
semistaticsim/groundtruth/sim.py
semistaticsim/groundtruth/spoof_vmap.py
semistaticsim/groundtruth/transmat_utils.py
semistaticsim/groundtruth/utils.py
semistaticsim/groundtruth/viz.py
semistaticsim/keyboardcontrol/__init__.py
semistaticsim/keyboardcontrol/main.py
semistaticsim/keyboardcontrol/main_skillsim.py
semistaticsim/keyboardcontrol/postprocessing.py
semistaticsim/keyboardcontrol/rollout.py
semistaticsim/keyboardcontrol/config/config.yaml
semistaticsim/keyboardcontrol/config/hydra/launcher/sbatch.yaml
semistaticsim/keyboardcontrol/config/hydra/sweep/sbatch.yaml
semistaticsim/keyboardcontrol/config/mode/auto.yaml
semistaticsim/keyboardcontrol/config/mode/keyboard.yaml
semistaticsim/keyboardcontrol/config/mode/rollout.yaml
semistaticsim/rendering/__init__.py
semistaticsim/rendering/ai2thor_hippo_controller.py
semistaticsim/rendering/floor.py
semistaticsim/rendering/simulation/__init__.py
semistaticsim/rendering/simulation/ai2thor_metadata_reader.py
semistaticsim/rendering/simulation/humanviewing.py
semistaticsim/rendering/simulation/skill_simulator.py
semistaticsim/rendering/simulation/spatialutils/__init__.py
semistaticsim/rendering/simulation/spatialutils/motion_planning.py
semistaticsim/rendering/simulation/spatialutils/proximity_spatial_funcs.py
semistaticsim/rendering/utils/__init__.py
semistaticsim/rendering/utils/dict2xyztup.py
semistaticsim/rendering/utils/dict_utils.py
semistaticsim/rendering/utils/spinner.py
semistaticsim-0.6.0.dist-info/METADATA
semistaticsim-0.6.0.dist-info/WHEEL
semistaticsim-0.6.0.dist-info/top_level.txt
semistaticsim-0.6.0.dist-info/RECORD
