Metadata-Version: 2.4
Name: semistaticsim
Version: 0.6.0
Summary: Add your description here
Requires-Python: >=3.12
Requires-Dist: ai2thor>=5.0.0
Requires-Dist: flax==0.12.0
Requires-Dist: hydra-core>=1.3.2
Requires-Dist: ipdb>=0.13.13
Requires-Dist: jax==0.8.1; sys_platform == "darwin"
Requires-Dist: jax[cuda12]==0.8.1; sys_platform == "linux"
Requires-Dist: matplotlib>=3.9.0
Requires-Dist: moviepy>=2.2.1
Requires-Dist: natsort>=8.4.0
Requires-Dist: networkx>=3.5
Requires-Dist: numpy==2.1.2
Requires-Dist: open3d>=0.19.0
Requires-Dist: openai>=2.0.0
Requires-Dist: polars>=1.33.1
Requires-Dist: prior>=1.0.3
Requires-Dist: scienceplots>=2.2.0
Requires-Dist: seaborn>=0.13.2
Requires-Dist: shapely>=2.1.2
Requires-Dist: tenacity>=9.1.2
Requires-Dist: tiktoken>=0.11.0
Requires-Dist: wheel>=0.45.1
Requires-Dist: hydra-submitit-launcher
Provides-Extra: dev
Requires-Dist: black; extra == "dev"
